<?xml version="1.0" encoding="utf-8" ?><dwsync><file name="aeras.css" server="people.wku.edu//export/home/lly32243/" local="3784564617" remote="3784564963" Dst="-1" /><file name="orchardcraft.css" server="people.wku.edu//export/home/lly32243/" local="3784564733" remote="3784565496" Dst="-1" /><file name="bright.css" server="people.wku.edu//export/home/lly32243/" local="3784564733" remote="3784565493" Dst="-1" /><file name="sunkissed.css" server="people.wku.edu//export/home/lly32243/" local="3784564733" remote="3784565497" Dst="-1" /><file name="barkday bites.css" server="people.wku.edu//export/home/lly32243/" local="3784564733" remote="3784565493" Dst="-1" /><file name="barkday bites.html" server="people.wku.edu//export/home/lly32243/" local="3784481385" remote="3784565493" Dst="-1" /><file name="contact.css" server="people.wku.edu//export/home/lly32243/" local="3784567183" remote="3784635424" Dst="-1" /><file name="contact.html" server="people.wku.edu//export/home/lly32243/" local="3784636381" remote="3784636427" Dst="-1" /><file name="difky.css" server="people.wku.edu//export/home/lly32243/" local="3784564733" remote="3784565495" Dst="-1" /><file name="orchardcraft.html" server="people.wku.edu//export/home/lly32243/" local="3784481385" remote="3784565496" Dst="-1" /><file name="sabor a sol.css" server="people.wku.edu//export/home/lly32243/" local="3784564733" remote="3784565496" Dst="-1" /><file name="scoops and swirls.css" server="people.wku.edu//export/home/lly32243/" local="3784564733" remote="3784565496" Dst="-1" /><file name="thrive.css" server="people.wku.edu//export/home/lly32243/" local="3784564733" remote="3784565498" Dst="-1" /><file name="about.css" server="people.wku.edu//export/home/lly32243/" local="3784552658" remote="3784564958" Dst="-1" /><file name="index.css" server="people.wku.edu//export/home/lly32243/" local="3784564845" remote="3784565495" Dst="-1" /><file name="index.html" server="people.wku.edu//export/home/lly32243/" local="3784564529" remote="3784565495" Dst="-1" /><file name="process-form.php" server="people.wku.edu//export/home/lly32243/" local="3784556630" remote="3784565494" Dst="-1" /><file name="thankyou.css" server="people.wku.edu//export/home/lly32243/" local="3784563517" remote="3784565497" Dst="-1" /><file name="about.html" server="people.wku.edu//export/home/lly32243/" local="3784548571" remote="3784564958" Dst="-1" /><file name="aeras2.html" server="people.wku.edu//export/home/lly32243/" local="3784481385" remote="3784564963" Dst="-1" /><file name="bright2.html" server="people.wku.edu//export/home/lly32243/" local="3784481409" remote="3784565494" Dst="-1" /><file name="difky2.html" server="people.wku.edu//export/home/lly32243/" local="3784481385" remote="3784565495" Dst="-1" /><file name="sabor.html" server="people.wku.edu//export/home/lly32243/" local="3784481385" remote="3784565496" Dst="-1" /><file name="scoops.html" server="people.wku.edu//export/home/lly32243/" local="3784481385" remote="3784565496" Dst="-1" /><file name="sunkissed2.html" server="people.wku.edu//export/home/lly32243/" local="3784481385" remote="3784565497" Dst="-1" /><file name="thank-you.html" server="people.wku.edu//export/home/lly32243/" local="3784563439" remote="3784565497" Dst="-1" /><file name="thrive2.html" server="people.wku.edu//export/home/lly32243/" local="3784481385" remote="3784565498" Dst="-1" /></dwsync>